{
  "_generated": "GERADO por `npm run build:catalog` — NÃO edite à mão. Fonte: pastas de bloco em CATALOG_DIR.",
  "catalogVersion": 1,
  "count": 43,
  "blocks": [
    {
      "type": "__example",
      "kind": "title",
      "name": "Bloco de exemplo",
      "description": "Placeholder que valida o auto-registro do catálogo (F0.4). Não use em produção.",
      "source": "custom",
      "propsSchema": {
        "type": "object",
        "additionalProperties": false,
        "properties": {
          "label": {
            "type": "string"
          }
        }
      },
      "defaultProps": {
        "label": "Auto-registrado ✔"
      },
      "version": "0.0.0"
    },
    {
      "type": "alert",
      "kind": "text",
      "name": "Alerta",
      "description": "Aviso/observação em destaque (título + descrição), com variante de cor + ícone, ícone opcional e botão de fechar opcional.",
      "source": "vitrine:alert",
      "propsSchema": {
        "type": "object",
        "additionalProperties": false,
        "required": [
          "title"
        ],
        "properties": {
          "variant": {
            "type": "string",
            "enum": [
              "default",
              "info",
              "success",
              "warning",
              "error",
              "destructive"
            ],
            "default": "default",
            "description": "Variante semântica (define cor da borda/texto + ícone). ENUM FECHADO (sem input livre).",
            "oneOf": [
              {
                "const": "default",
                "description": "Neutro (card) — ícone ℹ Info. Aviso genérico sem conotação."
              },
              {
                "const": "info",
                "description": "Informativo (azul/sky) — ícone ℹ Info. Contexto/dica."
              },
              {
                "const": "success",
                "description": "Sucesso (verde/emerald) — ícone ✓ CircleCheck. Operação concluída/meta atingida."
              },
              {
                "const": "warning",
                "description": "Atenção (âmbar/amber) — ícone ⚠ TriangleAlert. Algo requer cuidado."
              },
              {
                "const": "error",
                "description": "Erro (vermelho) — ícone ✕ CircleX. Falha/valor crítico. Alias semântico de destructive."
              },
              {
                "const": "destructive",
                "description": "Destrutivo (vermelho, token --destructive do DS) — ícone CircleAlert. Ação irreversível/alerta forte."
              }
            ]
          },
          "title": {
            "type": "string",
            "description": "Título do alerta (obrigatório)."
          },
          "description": {
            "type": "string",
            "description": "Texto do corpo do alerta (opcional)."
          },
          "showIcon": {
            "type": "boolean",
            "default": true,
            "description": "Mostra o ícone semântico (ℹ/✓/⚠/✕) conforme a variante. false oculta o ícone."
          },
          "dismissible": {
            "type": "boolean",
            "default": false,
            "description": "Quando true, exibe um botão X no canto que fecha o alerta (estado local — ao fechar, o bloco some da tela)."
          }
        }
      },
      "defaultProps": {
        "variant": "default",
        "title": "Atenção",
        "description": "A inadimplência da zona Leste ultrapassou 30% no período.",
        "showIcon": true,
        "dismissible": false
      },
      "version": "1.0.0"
    },
    {
      "type": "area_chart",
      "kind": "chart",
      "name": "Gráfico de Área",
      "description": "Série temporal preenchida; mostra volume/tendência ao longo do tempo (suporta múltiplas séries).",
      "source": "vitrine:area-chart-tremor",
      "propsSchema": {
        "type": "object",
        "additionalProperties": false,
        "properties": {
          "type": {
            "type": "string",
            "enum": [
              "default",
              "stacked",
              "percent"
            ],
            "default": "default",
            "description": "Composição das áreas: \"default\" (sobrepostas, cada série da baseline ao valor), \"stacked\" (empilhadas) ou \"percent\" (100% normalizado)."
          },
          "fill": {
            "type": "string",
            "enum": [
              "gradient",
              "solid",
              "none"
            ],
            "default": "gradient",
            "description": "Preenchimento da área: \"gradient\" (cor da série → transparente), \"solid\" (cor opaca com 25% alpha) ou \"none\" (só a linha de topo)."
          },
          "showLegend": {
            "type": "boolean",
            "default": true,
            "description": "Exibe bloco de legenda clicável abaixo do SVG (uma bolinha por série + rótulo)."
          },
          "showGridLines": {
            "type": "boolean",
            "default": true,
            "description": "Exibe linhas de grade horizontais tracejadas (alinhadas aos ticks do eixo Y)."
          },
          "palette": {
            "type": "string",
            "enum": [
              "single",
              "multi",
              "none"
            ],
            "default": "multi",
            "description": "Modo de paleta: \"multi\" (default) = cicla chart-1..5 por série; \"single\" = força accent em todas; \"none\" = sem distinção de cor."
          },
          "accent": {
            "type": "string",
            "enum": [
              "chart-1",
              "chart-2",
              "chart-3",
              "chart-4",
              "chart-5",
              "primary"
            ],
            "default": "chart-1",
            "description": "Cor base da(s) série(s). Aceita enum DS (chart-1..5, primary), classe Tailwind (bg-purple-500), ou cor CSS (#40E0D0, rgb(), linear-gradient(), var(--chart-1)). Aplicada como stroke/fill via classe Tailwind ou style.stroke quando CSS custom."
          }
        }
      },
      "dataContract": {
        "shape": "series",
        "spec": {
          "x": {
            "type": "temporal",
            "required": true
          },
          "y": {
            "type": "number",
            "required": true
          },
          "series": {
            "type": "category",
            "required": false
          }
        },
        "example": [
          {
            "x": "2026-01",
            "y": 120,
            "series": "Receita"
          },
          {
            "x": "2026-01",
            "y": 80,
            "series": "Despesa"
          }
        ]
      },
      "defaultProps": {
        "type": "default",
        "fill": "gradient",
        "showLegend": true,
        "showGridLines": true,
        "palette": "multi",
        "accent": "chart-1"
      },
      "maxRows": 5000,
      "version": "1.0.0"
    },
    {
      "type": "background_beams",
      "kind": "layout",
      "name": "Background Beams",
      "description": "Fundo animado com feixes de luz — capa/hero de relatório com título.",
      "source": "vitrine:background-beams",
      "propsSchema": {
        "type": "object",
        "additionalProperties": false,
        "properties": {
          "title": {
            "type": "string"
          },
          "subtitle": {
            "type": "string"
          }
        }
      },
      "defaultProps": {
        "title": "Inteligência de dados",
        "subtitle": "Transforme números em decisões para a gestão municipal."
      },
      "version": "1.0.0"
    },
    {
      "type": "background_boxes",
      "kind": "layout",
      "name": "Background Boxes",
      "description": "Fundo isométrico de células que acendem no hover — capa decorativa com título.",
      "source": "vitrine:background-boxes",
      "propsSchema": {
        "type": "object",
        "additionalProperties": false,
        "properties": {
          "title": {
            "type": "string"
          },
          "subtitle": {
            "type": "string"
          }
        }
      },
      "defaultProps": {
        "title": "Painel da Prefeitura",
        "subtitle": "Indicadores e relatórios em um só lugar."
      },
      "version": "1.0.0"
    },
    {
      "type": "bar_chart",
      "kind": "chart",
      "name": "Gráfico de Barras",
      "description": "Compara valores entre categorias em barras verticais (colunas) ou horizontais. Suporta empilhamento (stacked) quando os dados têm múltiplas séries (campo `series`).",
      "source": "vitrine:bar-chart",
      "propsSchema": {
        "type": "object",
        "additionalProperties": false,
        "properties": {
          "stacked": {
            "type": "boolean",
            "default": false,
            "description": "Empilha as séries em cada coluna (requer dados MULTI-SÉRIE: pontos com o campo `series`). true = cada categoria do eixo X vira uma coluna com segmentos empilhados, um por série. false = barras planas (1 barra por ponto). LIMITAÇÃO: só vale na orientação \"vertical\"; em \"horizontal\" o empilhamento é ignorado (barras planas), mas a cor por série é preservada. Se não houver dados multi-série, degrada para barras planas."
          },
          "orientation": {
            "type": "string",
            "enum": [
              "vertical",
              "horizontal"
            ],
            "default": "vertical",
            "description": "Orientação das barras: \"vertical\" (colunas, default) ou \"horizontal\" (barras deitadas — bom para rótulos longos). O empilhamento (stacked) só funciona na vertical."
          },
          "accent": {
            "type": "string",
            "enum": [
              "chart-1",
              "chart-2",
              "chart-3",
              "chart-4",
              "chart-5",
              "primary"
            ],
            "default": "chart-1",
            "description": "Cor base das barras (usado em palette=\"single\"). Aceita enum DS (chart-1..5, primary), classe Tailwind (bg-purple-500) ou cor CSS (#40E0D0, rgb(), linear-gradient(), var(--chart-1)). Em palette=\"multi\" é IGNORADO (a paleta cíclica do DS vence)."
          },
          "palette": {
            "type": "string",
            "enum": [
              "single",
              "multi",
              "none"
            ],
            "default": "single",
            "description": "Modo de paleta AUTOMÁTICA: \"single\" (default) = todas as barras/séries com a mesma cor (accent); \"multi\" = cicla chart-1..5 por série/barra (accent custom é ignorado); \"none\" = sem cor (default do UI base). Sobrescrito por `seriesColors` quando este é fornecido."
          },
          "seriesColors": {
            "type": "array",
            "items": {
              "type": "string"
            },
            "description": "Cor por série, na ORDEM (índice 0 = primeira série, 1 = segunda, etc.). Cada item aceita enum DS (chart-1..5, primary), classe Tailwind (bg-purple-500) ou cor CSS (#40E0D0, rgb(), linear-gradient()). SOBRESCREVE a palette automática para aquela série. Se omitido, usa `palette` (multi cicla chart-1..5, single usa accent). Use principalmente com stacked=true para fixar manualmente a cor de cada série empilhada."
          },
          "valueFormat": {
            "type": "string",
            "enum": [
              "BRL",
              "compactBRL",
              "number",
              "compactNumber",
              "percent"
            ],
            "default": "compactBRL",
            "description": "Formato PT-BR do valor exibido no topo da barra/coluna + tooltip. ENUM FECHADO (sem input livre): BRL, compactBRL, number, compactNumber, percent.",
            "oneOf": [
              {
                "const": "BRL",
                "description": "formatBRL — moeda BRL completa (ex.: \"R$ 2.609.946.157,73\")."
              },
              {
                "const": "compactBRL",
                "description": "formatCompactBRL — moeda BRL compacta (ex.: \"R$ 2,61 bi\"). DEFAULT."
              },
              {
                "const": "number",
                "description": "formatNumberBR — número PT-BR com milhar (ex.: \"1.234.567,8\")."
              },
              {
                "const": "compactNumber",
                "description": "formatCompactNumberBR — número compacto (ex.: \"2,61 bi\")."
              },
              {
                "const": "percent",
                "description": "formatPercentBR — percentual a partir de FRAÇÃO (ex.: 0.125 → \"12,5%\")."
              }
            ]
          }
        }
      },
      "dataContract": {
        "shape": "series",
        "spec": {
          "x": {
            "type": "category",
            "required": true
          },
          "y": {
            "type": "number",
            "required": true
          },
          "series": {
            "type": "category",
            "required": false
          }
        },
        "example": [
          {
            "x": "Jan",
            "y": 120,
            "series": "Receita"
          },
          {
            "x": "Jan",
            "y": 95,
            "series": "Despesa"
          },
          {
            "x": "Fev",
            "y": 138,
            "series": "Receita"
          },
          {
            "x": "Fev",
            "y": 110,
            "series": "Despesa"
          }
        ]
      },
      "defaultProps": {
        "orientation": "vertical",
        "stacked": false,
        "accent": "chart-1",
        "palette": "single",
        "valueFormat": "compactBRL"
      },
      "minColumns": 1,
      "maxRows": 5000,
      "version": "1.1.0"
    },
    {
      "type": "bar_list",
      "kind": "chart",
      "name": "Lista de Barras (ranking)",
      "description": "Ranking de categorias (Top N) — barra proporcional ao valor, ordenada.",
      "source": "vitrine:bar-list-tremor",
      "propsSchema": {
        "type": "object",
        "additionalProperties": false,
        "properties": {
          "sortOrder": {
            "type": "string",
            "enum": [
              "ascending",
              "descending",
              "none"
            ],
            "default": "descending",
            "description": "Ordem de exibição dos itens: \"descending\" (default, maior primeiro), \"ascending\" (menor primeiro) ou \"none\" (preserva a ordem do dataset)."
          },
          "palette": {
            "type": "string",
            "enum": [
              "single",
              "multi",
              "none"
            ],
            "default": "single",
            "description": "Modo de paleta: \"single\" (default) = TODAS as barras com a mesma cor (accent); \"multi\" = cicla chart-1..5 por item (helper paletteClass(i) via BarListTremorItem.barClassName); \"none\" = sem distinção (usa o default do UI base)."
          },
          "accent": {
            "type": "string",
            "enum": [
              "chart-1",
              "chart-2",
              "chart-3",
              "chart-4",
              "chart-5",
              "primary"
            ],
            "default": "chart-1",
            "description": "Cor base da barra (só usado em palette=\"single\"). Aceita enum DS (chart-1..5, primary), classe Tailwind (bg-purple-500), ou cor CSS (#40E0D0, rgb(), linear-gradient(), var(--chart-1))."
          },
          "textColor": {
            "type": "string",
            "description": "Cor do texto que fica DENTRO da barra. Por padrão (vazio) é AUTOMÁTICA por contraste (luminância WCAG da cor da barra → preto em barra clara, branco em barra escura) — sempre legível. Informe só para forçar: cor CSS (#000, rgb(255,255,255), white) ou classe Tailwind (text-white, text-black)."
          }
        }
      },
      "dataContract": {
        "shape": "categorical",
        "spec": {
          "label": {
            "type": "category",
            "required": true
          },
          "value": {
            "type": "number",
            "required": true
          }
        },
        "example": [
          {
            "label": "IPTU",
            "value": 4200
          },
          {
            "label": "ISS",
            "value": 3100
          }
        ]
      },
      "defaultProps": {
        "sortOrder": "descending",
        "palette": "single",
        "accent": "chart-1"
      },
      "maxRows": 5000,
      "version": "1.0.0"
    },
    {
      "type": "bento_grid",
      "kind": "layout",
      "name": "Bento Grid",
      "description": "Container de layout em mosaico \"bento\". Renderiza sub-blocos (gráficos/cards/tabelas) num grid; cada filho usa `span` (largura 1..12) e `rowSpan` (altura). Use `block.blocks` para os filhos. Props: columns, gap.",
      "source": "custom",
      "propsSchema": {
        "type": "object",
        "additionalProperties": false,
        "properties": {
          "columns": {
            "type": "integer",
            "minimum": 1,
            "maximum": 12,
            "default": 12,
            "description": "Número de colunas do grid bento (1..12). O `span` de cada filho é relativo a este total. Default: 12 (alinha com o grid do dashboard)."
          },
          "gap": {
            "type": "string",
            "enum": [
              "sm",
              "md",
              "lg"
            ],
            "default": "md",
            "description": "Espaçamento entre as células do mosaico: sm (compacto), md (default), lg (espaçado)."
          },
          "autoRows": {
            "type": "string",
            "enum": [
              "sm",
              "md",
              "lg"
            ],
            "default": "md",
            "description": "Altura base de cada linha do mosaico (afeta o efeito do `rowSpan` dos filhos): sm (~8rem), md (~11rem, default), lg (~14rem)."
          }
        }
      },
      "defaultProps": {
        "columns": 12,
        "gap": "md",
        "autoRows": "md"
      },
      "version": "2.0.0"
    },
    {
      "type": "callout",
      "kind": "text",
      "name": "Callout",
      "description": "Banner de destaque semântico (info/sucesso/aviso/erro) com título e texto.",
      "source": "vitrine:callout-tremor",
      "propsSchema": {
        "type": "object",
        "additionalProperties": false,
        "required": [
          "title"
        ],
        "properties": {
          "variant": {
            "type": "string",
            "enum": [
              "default",
              "info",
              "success",
              "warning",
              "error"
            ],
            "description": "Preset semântico que define as cores base da caixa, do texto e do ícone (default | info=azul | success=verde | warning=amarelo | error=vermelho). boxColor/textColor sobrescrevem por cima."
          },
          "title": {
            "type": "string",
            "description": "Título em destaque (linha 1, ao lado do ícone). Obrigatório."
          },
          "description": {
            "type": "string",
            "description": "Corpo do banner (linha 2, abaixo do título)."
          },
          "boxColor": {
            "type": "string",
            "description": "Cor da CAIXA (fundo). Sobrescreve a cor do variant. INDEPENDENTE do texto. Aceita enum DS (chart-1..5, primary), classe Tailwind (bg-purple-500) ou cor CSS (#40E0D0, rgb(), gradient). Vazio = usa a cor do variant."
          },
          "textColor": {
            "type": "string",
            "description": "Cor do TEXTO (título + corpo + ícone). Sobrescreve a cor do variant. INDEPENDENTE da caixa. Mesmo formato de boxColor (enum DS, classe Tailwind ou cor CSS). Vazio = herda a cor do variant."
          },
          "showIcon": {
            "type": "boolean",
            "description": "Mostra o ícone semântico à esquerda do título. Default: true."
          }
        }
      },
      "defaultProps": {
        "variant": "success",
        "title": "Meta atingida",
        "description": "A arrecadação do trimestre superou a meta em 8%.",
        "showIcon": true
      },
      "version": "1.1.0"
    },
    {
      "type": "card_hover",
      "kind": "layout",
      "name": "Cards com Hover",
      "description": "Grade de cards com destaque animado ao passar o mouse.",
      "source": "vitrine:card-hover-effect",
      "propsSchema": {
        "type": "object",
        "additionalProperties": false,
        "properties": {
          "items": {
            "type": "array",
            "items": {
              "type": "object",
              "additionalProperties": false,
              "required": [
                "title"
              ],
              "properties": {
                "title": {
                  "type": "string"
                },
                "description": {
                  "type": "string"
                },
                "link": {
                  "type": "string"
                }
              }
            }
          }
        }
      },
      "defaultProps": {
        "items": [
          {
            "title": "Arrecadação",
            "description": "Receita consolidada por tributo.",
            "link": "#"
          },
          {
            "title": "Dívida ativa",
            "description": "Estoque e recuperação da dívida ativa.",
            "link": "#"
          },
          {
            "title": "Despesas",
            "description": "Execução orçamentária por órgão.",
            "link": "#"
          }
        ]
      },
      "version": "1.0.0"
    },
    {
      "type": "collapsible_block",
      "kind": "layout",
      "name": "Seção Colapsável",
      "description": "Seção com cabeçalho clicável que expande/recolhe o conteúdo.",
      "source": "vitrine:collapsible-section",
      "propsSchema": {
        "type": "object",
        "additionalProperties": false,
        "required": [
          "title"
        ],
        "properties": {
          "title": {
            "type": "string"
          },
          "body": {
            "type": "string"
          },
          "defaultOpen": {
            "type": "boolean"
          }
        }
      },
      "defaultProps": {
        "title": "Detalhes da apuração",
        "body": "A consulta considera os lançamentos com vencimento dentro do período selecionado.",
        "defaultOpen": true
      },
      "version": "1.0.0"
    },
    {
      "type": "dashboard_panel",
      "kind": "layout",
      "name": "Painel de Dashboard",
      "description": "Contêiner de painel com título, descrição e corpo — agrupa conteúdo de um relatório.",
      "source": "vitrine:dashboard-panel",
      "propsSchema": {
        "type": "object",
        "additionalProperties": false,
        "required": [
          "title"
        ],
        "properties": {
          "title": {
            "type": "string"
          },
          "description": {
            "type": "string"
          },
          "body": {
            "type": "string"
          },
          "variant": {
            "type": "string",
            "enum": [
              "card",
              "framed"
            ]
          }
        }
      },
      "defaultProps": {
        "title": "Arrecadação consolidada",
        "description": "Indicadores do mês corrente",
        "body": "A receita acumulada superou a meta em 8% no período, puxada pelo ISS e pelo IPTU.",
        "variant": "card"
      },
      "version": "1.0.0"
    },
    {
      "type": "data_table",
      "kind": "chart",
      "name": "Tabela Rica",
      "description": "Tabela com busca, ordenação e paginação (colunas tipadas). Para datasets tabulares.",
      "source": "vitrine:data-table",
      "propsSchema": {
        "type": "object",
        "additionalProperties": false,
        "properties": {
          "pageSize": {
            "type": "integer",
            "minimum": 1
          },
          "filterPlaceholder": {
            "type": "string"
          }
        }
      },
      "dataContract": {
        "shape": "table",
        "spec": {
          "columns": {
            "type": "array",
            "required": true
          },
          "rows": {
            "type": "array",
            "required": true
          }
        },
        "example": {
          "columns": [
            {
              "key": "municipio",
              "label": "Município",
              "type": "string"
            },
            {
              "key": "valor",
              "label": "Valor",
              "type": "number"
            }
          ],
          "rows": [
            {
              "municipio": "Centro",
              "valor": 1000
            }
          ]
        }
      },
      "defaultProps": {
        "pageSize": 5
      },
      "maxRows": 5000,
      "version": "1.0.0"
    },
    {
      "type": "divider",
      "kind": "layout",
      "name": "Divisor",
      "description": "Linha divisória com rótulo central opcional — separa seções de um relatório.",
      "source": "vitrine:divider-tremor",
      "propsSchema": {
        "type": "object",
        "additionalProperties": false,
        "properties": {
          "label": {
            "type": "string"
          },
          "orientation": {
            "type": "string",
            "enum": [
              "horizontal",
              "vertical"
            ]
          }
        }
      },
      "defaultProps": {
        "label": "Resumo do período",
        "orientation": "horizontal"
      },
      "version": "1.0.0"
    },
    {
      "type": "donut",
      "kind": "chart",
      "name": "Donut",
      "description": "Distribuição de um total entre categorias (label + value).",
      "source": "vitrine:donut-chart",
      "propsSchema": {
        "type": "object",
        "additionalProperties": false,
        "properties": {
          "showLegend": {
            "type": "boolean",
            "default": true,
            "description": "Exibe legenda clicável ao lado (uma linha por categoria com bolinha, valor absoluto e percentual). Em listas longas (6+ categorias) vira grade de 2 colunas com rolagem."
          },
          "centerLabel": {
            "type": "string",
            "description": "Rótulo exibido no centro do donut quando NÃO há hover em nenhum segmento (abaixo dele aparece o VALOR TOTAL, soma das fatias). Default: \"Total\"."
          },
          "palette": {
            "type": "string",
            "enum": [
              "single",
              "multi",
              "none"
            ],
            "default": "single",
            "description": "Modo de paleta: \"single\" (default) = TODAS as fatias na MESMA cor (accent), variando a opacidade por fatia para mantê-las distinguíveis; \"multi\" = cicla chart-1..5 por categoria (accent custom é IGNORADO — a paleta do DS vence); \"none\" = sem cor (currentColor herdado, sem distinção)."
          },
          "accent": {
            "type": "string",
            "enum": [
              "chart-1",
              "chart-2",
              "chart-3",
              "chart-4",
              "chart-5",
              "primary"
            ],
            "default": "chart-1",
            "description": "Cor base aplicada aos segmentos (só usado em palette=\"single\"; em \"multi\" a paleta cíclica do DS vence). Aceita enum DS (chart-1..5, primary), classe Tailwind (stroke-purple-500), ou cor CSS (#40E0D0, rgb(), linear-gradient(), var(--chart-1))."
          },
          "valueFormat": {
            "type": "string",
            "enum": [
              "BRL",
              "compactBRL",
              "number",
              "compactNumber",
              "percent"
            ],
            "default": "compactBRL",
            "description": "Formato PT-BR do valor exibido no centro do donut (total/fatia) + legenda. ENUM FECHADO (sem input livre).",
            "oneOf": [
              {
                "const": "BRL",
                "description": "formatBRL — moeda BRL completa (ex.: \"R$ 2.609.946.157,73\")."
              },
              {
                "const": "compactBRL",
                "description": "formatCompactBRL — moeda BRL compacta (ex.: \"R$ 2,61 bi\"). DEFAULT."
              },
              {
                "const": "number",
                "description": "formatNumberBR — número PT-BR com milhar (ex.: \"1.234.567,8\")."
              },
              {
                "const": "compactNumber",
                "description": "formatCompactNumberBR — número compacto (ex.: \"2,61 bi\")."
              },
              {
                "const": "percent",
                "description": "formatPercentBR — percentual a partir de FRAÇÃO (ex.: 0.125 → \"12,5%\")."
              }
            ]
          }
        }
      },
      "dataContract": {
        "shape": "categorical",
        "spec": {
          "label": {
            "type": "category",
            "required": true
          },
          "value": {
            "type": "number",
            "required": true
          }
        },
        "example": [
          {
            "label": "Quitado",
            "value": 62
          },
          {
            "label": "Em aberto",
            "value": 38
          }
        ]
      },
      "defaultProps": {
        "showLegend": true,
        "palette": "single",
        "accent": "chart-1",
        "valueFormat": "compactBRL"
      },
      "version": "1.0.0"
    },
    {
      "type": "expandable_cards",
      "kind": "layout",
      "name": "Cards Expansíveis",
      "description": "Lista de cards que expandem para um modal com detalhes ao clicar.",
      "source": "vitrine:expandable-cards",
      "propsSchema": {
        "type": "object",
        "additionalProperties": false,
        "properties": {
          "cards": {
            "type": "array",
            "items": {
              "type": "object",
              "additionalProperties": false,
              "required": [
                "title"
              ],
              "properties": {
                "title": {
                  "type": "string"
                },
                "description": {
                  "type": "string"
                },
                "src": {
                  "type": "string"
                },
                "ctaText": {
                  "type": "string"
                },
                "ctaLink": {
                  "type": "string"
                },
                "content": {
                  "type": "string"
                }
              }
            }
          }
        }
      },
      "defaultProps": {
        "cards": [
          {
            "title": "Relatório de Arrecadação",
            "description": "Consolidação mensal",
            "src": "https://picsum.photos/seed/arrecadacao/200/200",
            "ctaText": "Abrir",
            "ctaLink": "#",
            "content": "Receita por tributo, evolução mês a mês e comparação com a meta do exercício."
          },
          {
            "title": "Dívida Ativa",
            "description": "Estoque e recuperação",
            "src": "https://picsum.photos/seed/divida/200/200",
            "ctaText": "Abrir",
            "ctaLink": "#",
            "content": "Estoque da dívida ativa, taxa de recuperação e parcelamentos em andamento."
          },
          {
            "title": "Despesas por Órgão",
            "description": "Execução orçamentária",
            "src": "https://picsum.photos/seed/despesas/200/200",
            "ctaText": "Abrir",
            "ctaLink": "#",
            "content": "Empenhado, liquidado e pago por secretaria, com saldo orçamentário disponível."
          }
        ]
      },
      "version": "1.0.0"
    },
    {
      "type": "flip_words",
      "kind": "title",
      "name": "Flip Words",
      "description": "Título com palavra que troca animadamente — ótimo para capas/headers de relatório.",
      "source": "vitrine:flip-words",
      "propsSchema": {
        "type": "object",
        "additionalProperties": false,
        "required": [
          "words"
        ],
        "properties": {
          "prefix": {
            "type": "string"
          },
          "words": {
            "type": "array",
            "items": {
              "type": "string"
            }
          },
          "duration": {
            "type": "integer",
            "minimum": 500
          }
        }
      },
      "defaultProps": {
        "prefix": "Dados que são",
        "words": [
          "claros",
          "rápidos",
          "acionáveis"
        ],
        "duration": 2200
      },
      "version": "1.0.0"
    },
    {
      "type": "funnel_stage",
      "kind": "chart",
      "name": "Etapa de Funil",
      "description": "Painel COLAPSÁVEL de uma ETAPA de funil temporal (N1/N2/N3...). Header com resumo (quantidade + % do universo + valor), barra de participação segmentada e, ao expandir, tabela de desfechos (ícone + título + descrição + quantidade + valor original + valor atualizado) com linha de total e notas. Shape `table`: cada linha tem a coluna `tipo` (resumo|desfecho|total|nota) que define seu papel. Componha com UNION ALL (queries pequenas). Colunas por tipo: resumo{quantidade,pct(fração 0..1),valor}; desfecho{icone,desfecho,descricao,quantidade,quantidade_label?,valor_original,valor_atualizado}; total{desfecho,quantidade,valor_original,valor_atualizado}; nota{desfecho,descricao,valor_atualizado?}.",
      "source": "custom",
      "propsSchema": {
        "type": "object",
        "additionalProperties": false,
        "required": [
          "stageLabel"
        ],
        "properties": {
          "stageLabel": {
            "type": "string",
            "description": "Rótulo da etapa no header (ex.: \"N1 · MOMENTO LANÇAMENTO\")."
          },
          "accent": {
            "type": "string",
            "enum": [
              "blue",
              "red",
              "green",
              "amber",
              "violet",
              "slate"
            ],
            "description": "Cor base da etapa (texto de destaque + barra). blue (default) p/ fases iniciais; red p/ estoque/risco; amber/green/violet/slate p/ variações."
          },
          "defaultOpen": {
            "type": "boolean",
            "description": "Se a etapa começa expandida (mostrando a tabela). false (default) = só header + resumo + barra."
          },
          "barLabel": {
            "type": "string",
            "description": "Legenda exibida sob a barra (ex.: \"valor total lançado (VL_ORIGINAL)\")."
          },
          "valueFormat": {
            "type": "string",
            "enum": [
              "BRL",
              "compactBRL"
            ],
            "description": "Formato dos valores monetários. BRL = completo (R$ 3.745.086.826,03, default); compactBRL = compacto (\"R$ 3,74 bi\")."
          }
        }
      },
      "dataContract": {
        "shape": "table",
        "spec": {
          "columns": {
            "type": "array",
            "required": true
          },
          "rows": {
            "type": "array",
            "required": true
          }
        },
        "example": {
          "columns": [
            {
              "key": "tipo",
              "label": "tipo",
              "type": "string"
            },
            {
              "key": "desfecho",
              "label": "desfecho",
              "type": "string"
            },
            {
              "key": "quantidade",
              "label": "quantidade",
              "type": "number"
            },
            {
              "key": "valor_original",
              "label": "valor_original",
              "type": "number"
            },
            {
              "key": "valor_atualizado",
              "label": "valor_atualizado",
              "type": "number"
            }
          ],
          "rows": [
            {
              "tipo": "resumo",
              "quantidade": 10835362,
              "pct": 1,
              "valor": 3745086826.03
            },
            {
              "tipo": "desfecho",
              "icone": "CircleCheck",
              "desfecho": "Pago como lançamento",
              "descricao": "Pago e nunca inscrito em Dívida Ativa.",
              "quantidade": 8060686,
              "valor_original": 2767231605.76,
              "valor_atualizado": 5250514766.99
            },
            {
              "tipo": "total",
              "desfecho": "Total lançado",
              "quantidade": 10835362,
              "valor_original": 3745086826.03,
              "valor_atualizado": 8794434214.41
            }
          ]
        }
      },
      "defaultProps": {
        "accent": "blue",
        "defaultOpen": false,
        "valueFormat": "BRL"
      },
      "maxRows": 50,
      "version": "1.0.0"
    },
    {
      "type": "glowing_effect",
      "kind": "layout",
      "name": "Efeito de Brilho",
      "description": "Borda com brilho que reage ao ponteiro — destaca um card.",
      "source": "vitrine:glowing-effect",
      "propsSchema": {
        "type": "object",
        "additionalProperties": false,
        "properties": {
          "title": {
            "type": "string"
          },
          "description": {
            "type": "string"
          },
          "variant": {
            "type": "string",
            "enum": [
              "default",
              "white"
            ]
          }
        }
      },
      "defaultProps": {
        "title": "Painel em destaque",
        "description": "Passe o mouse sobre o card para ativar o brilho.",
        "variant": "default"
      },
      "version": "1.0.0"
    },
    {
      "type": "h_bar_chart",
      "kind": "chart",
      "name": "Barras Horizontais",
      "description": "Compara valores entre categorias em barras horizontais (rótulos longos cabem melhor).",
      "source": "vitrine:h-bar-chart",
      "propsSchema": {
        "type": "object",
        "additionalProperties": false,
        "properties": {
          "palette": {
            "type": "string",
            "enum": [
              "single",
              "multi",
              "none"
            ],
            "default": "single",
            "description": "Modo de paleta: \"single\" (default) = TODAS as barras com a mesma cor (accent); \"multi\" = cicla chart-1..5 por item (helper paletteClass(i) via HBarChartDatum.barClassName) — accent custom é IGNORADO nesse modo (a paleta do DS vence); \"none\" = sem distinção (default do UI base)."
          },
          "accent": {
            "type": "string",
            "enum": [
              "chart-1",
              "chart-2",
              "chart-3",
              "chart-4",
              "chart-5",
              "primary"
            ],
            "default": "chart-1",
            "description": "Cor base da barra (só usado em palette=\"single\"; em \"multi\" a paleta cíclica do DS vence). Aceita enum DS (chart-1..5, primary), classe Tailwind (bg-purple-500), ou cor CSS (#40E0D0, rgb(), linear-gradient(), var(--chart-1))."
          },
          "valueFormat": {
            "type": "string",
            "enum": [
              "BRL",
              "compactBRL",
              "number",
              "compactNumber",
              "percent"
            ],
            "default": "compactBRL",
            "description": "Formato PT-BR do valor exibido no rótulo lateral + tooltip. ENUM FECHADO (sem input livre).",
            "oneOf": [
              {
                "const": "BRL",
                "description": "formatBRL — moeda BRL completa (ex.: \"R$ 2.609.946.157,73\")."
              },
              {
                "const": "compactBRL",
                "description": "formatCompactBRL — moeda BRL compacta (ex.: \"R$ 2,61 bi\"). DEFAULT."
              },
              {
                "const": "number",
                "description": "formatNumberBR — número PT-BR com milhar (ex.: \"1.234.567,8\")."
              },
              {
                "const": "compactNumber",
                "description": "formatCompactNumberBR — número compacto (ex.: \"2,61 bi\")."
              },
              {
                "const": "percent",
                "description": "formatPercentBR — percentual a partir de FRAÇÃO (ex.: 0.125 → \"12,5%\")."
              }
            ]
          }
        }
      },
      "dataContract": {
        "shape": "series",
        "spec": {
          "x": {
            "type": "category",
            "required": true
          },
          "y": {
            "type": "number",
            "required": true
          }
        },
        "example": [
          {
            "x": "Centro",
            "y": 1200
          },
          {
            "x": "Norte",
            "y": 980
          }
        ]
      },
      "defaultProps": {
        "palette": "single",
        "accent": "chart-1",
        "valueFormat": "compactBRL"
      },
      "minColumns": 1,
      "maxRows": 5000,
      "version": "1.0.0"
    },
    {
      "type": "hover_card",
      "kind": "layout",
      "name": "Hover Card",
      "description": "Cartão flutuante exibido ao passar o mouse sobre o gatilho.",
      "source": "vitrine:hover-card",
      "propsSchema": {
        "type": "object",
        "additionalProperties": false,
        "properties": {
          "triggerLabel": {
            "type": "string"
          },
          "title": {
            "type": "string"
          },
          "content": {
            "type": "string"
          }
        }
      },
      "defaultProps": {
        "triggerLabel": "@prefeitura",
        "title": "Prefeitura Municipal",
        "content": "Portal de indicadores e relatórios da gestão municipal."
      },
      "version": "1.0.0"
    },
    {
      "type": "invoice_table",
      "kind": "chart",
      "name": "Tabela de Fatura",
      "description": "Itens com quantidade × valor unitário e total no rodapé. Linhas: label, qty, unit.",
      "source": "vitrine:invoice-table",
      "propsSchema": {
        "type": "object",
        "additionalProperties": false,
        "properties": {
          "currency": {
            "type": "string"
          }
        }
      },
      "dataContract": {
        "shape": "table",
        "spec": {
          "columns": {
            "type": "array",
            "required": true
          },
          "rows": {
            "type": "array",
            "required": true
          }
        },
        "example": {
          "columns": [
            {
              "key": "label",
              "label": "Item",
              "type": "string"
            },
            {
              "key": "qty",
              "label": "Qtd.",
              "type": "number"
            },
            {
              "key": "unit",
              "label": "Valor",
              "type": "number"
            }
          ],
          "rows": [
            {
              "label": "Licença",
              "qty": 3,
              "unit": 1200
            }
          ]
        }
      },
      "defaultProps": {
        "currency": "BRL"
      },
      "maxRows": 1000,
      "version": "1.0.0"
    },
    {
      "type": "kpi",
      "kind": "chart",
      "name": "KPI",
      "description": "Métrica única (escalar) com rótulo e variação opcional.",
      "source": "vitrine:kpi-card",
      "propsSchema": {
        "type": "object",
        "additionalProperties": false,
        "properties": {
          "label": {
            "type": "string",
            "description": "Rótulo da métrica. Sobrescreve o rótulo vindo do dado (data.label)."
          },
          "valueFormat": {
            "type": "string",
            "enum": [
              "auto",
              "BRL",
              "compactBRL",
              "number",
              "compactNumber",
              "percent"
            ],
            "default": "auto",
            "description": "Formato PT-BR do valor exibido. \"auto\" (default) escolhe o melhor display pela unidade/magnitude (formatKpiValue); os demais FORÇAM o formato. ENUM FECHADO (sem input livre).",
            "oneOf": [
              {
                "const": "auto",
                "description": "formatKpiValue — escolhe automático: moeda compacta p/ unit BRL/USD/EUR, número compacto p/ magnitude ≥ 10 mil, número cheio caso contrário. DEFAULT."
              },
              {
                "const": "BRL",
                "description": "formatBRL — moeda BRL completa (ex.: \"R$ 1.284.000,00\")."
              },
              {
                "const": "compactBRL",
                "description": "formatCompactBRL — moeda BRL compacta (ex.: \"R$ 1,28 mi\")."
              },
              {
                "const": "number",
                "description": "formatNumberBR — número PT-BR com milhar (ex.: \"1.284.000\")."
              },
              {
                "const": "compactNumber",
                "description": "formatCompactNumberBR — número compacto (ex.: \"1,28 mi\")."
              },
              {
                "const": "percent",
                "description": "formatPercentBR — percentual a partir de FRAÇÃO (ex.: 0.125 → \"12,5%\")."
              }
            ]
          },
          "accent": {
            "type": "string",
            "enum": [
              "chart-1",
              "chart-2",
              "chart-3",
              "chart-4",
              "chart-5",
              "primary"
            ],
            "default": "chart-1",
            "description": "Cor de destaque do card (rail lateral + chip do ícone). Aceita enum DS (chart-1..5, primary), classe Tailwind (bg-purple-500) ou cor CSS (#40E0D0, rgb(), linear-gradient(), var(--chart-1)). Resolvida por resolveAccent()."
          },
          "icon": {
            "type": "string",
            "enum": [
              "DollarSign",
              "Banknote",
              "Coins",
              "Wallet",
              "PiggyBank",
              "CreditCard",
              "Receipt",
              "Landmark",
              "TrendingUp",
              "TrendingDown",
              "Activity",
              "BarChart3",
              "LineChart",
              "PieChart",
              "Target",
              "Gauge",
              "Percent",
              "Users",
              "UserCheck",
              "Building2",
              "MapPin",
              "FileText",
              "ClipboardList",
              "Calendar",
              "Clock",
              "AlertTriangle",
              "CheckCircle2",
              "Info",
              "ArrowUpRight",
              "ArrowDownRight"
            ],
            "description": "Ícone lucide-react exibido no canto do card. ENUM CURADO (set relevante p/ dashboards: financeiro/métricas/pessoas/status). Ex.: \"DollarSign\", \"TrendingUp\", \"Users\", \"Landmark\". Vazio = sem ícone."
          },
          "showDelta": {
            "type": "boolean",
            "default": true,
            "description": "Mostra a variação (delta) vs. período anterior. false = esconde."
          },
          "deltaPolarity": {
            "type": "string",
            "enum": [
              "up-good",
              "up-bad"
            ],
            "default": "up-good",
            "description": "Polaridade da variação: \"up-good\" (default) = subir é bom (delta positivo verde); \"up-bad\" = subir é ruim (delta positivo vermelho, ex.: inadimplência, custo)."
          }
        }
      },
      "dataContract": {
        "shape": "scalar",
        "spec": {
          "value": {
            "type": "number",
            "required": true
          },
          "label": {
            "type": "string",
            "required": false
          },
          "delta": {
            "type": "number",
            "required": false
          }
        },
        "example": {
          "value": 1284000,
          "label": "Total arrecadado",
          "unit": "BRL",
          "delta": 0.12
        }
      },
      "defaultProps": {
        "showDelta": true,
        "valueFormat": "auto",
        "accent": "chart-1",
        "deltaPolarity": "up-good"
      },
      "version": "1.0.0"
    },
    {
      "type": "leaderboard",
      "kind": "chart",
      "name": "Leaderboard",
      "description": "Ranking (Top N) com posição, avatar e barra de progresso proporcional ao valor.",
      "source": "vitrine:leaderboard-list",
      "propsSchema": {
        "type": "object",
        "additionalProperties": false,
        "properties": {
          "unit": {
            "type": "string"
          }
        }
      },
      "dataContract": {
        "shape": "categorical",
        "spec": {
          "label": {
            "type": "category",
            "required": true
          },
          "value": {
            "type": "number",
            "required": true
          }
        },
        "example": [
          {
            "label": "Ana Souza",
            "value": 1280
          },
          {
            "label": "Bruno Lima",
            "value": 980
          }
        ]
      },
      "defaultProps": {},
      "maxRows": 1000,
      "version": "1.0.0"
    },
    {
      "type": "line_chart",
      "kind": "chart",
      "name": "Gráfico de Linhas",
      "description": "Série temporal: evolução de um valor ao longo do tempo.",
      "source": "vitrine:line-chart",
      "propsSchema": {
        "type": "object",
        "additionalProperties": false,
        "properties": {
          "smooth": {
            "type": "boolean",
            "description": "Se true, desenha as linhas como curvas suaves (Catmull-Rom). Se false, segmentos retos (polyline)."
          },
          "area": {
            "type": "boolean",
            "default": true,
            "description": "Se true, preenche área abaixo de cada linha além do traço."
          },
          "palette": {
            "type": "string",
            "enum": [
              "single",
              "multi",
              "none"
            ],
            "default": "multi",
            "description": "Modo de paleta: \"multi\" (default) = cicla chart-1..5 por série; \"single\" = força accent em todas; \"none\" = sem distinção de cor."
          },
          "accent": {
            "type": "string",
            "enum": [
              "chart-1",
              "chart-2",
              "chart-3",
              "chart-4",
              "chart-5",
              "primary"
            ],
            "default": "chart-1",
            "description": "Cor base da(s) série(s). Aceita enum DS (chart-1..5, primary), classe Tailwind (bg-purple-500), ou cor CSS (#40E0D0, rgb(), linear-gradient(), var(--chart-1)). Aplicada como stroke via classe Tailwind ou style.stroke quando CSS custom."
          }
        }
      },
      "dataContract": {
        "shape": "series",
        "spec": {
          "x": {
            "type": "temporal",
            "required": true
          },
          "y": {
            "type": "number",
            "required": true
          },
          "series": {
            "type": "category",
            "required": false
          }
        },
        "example": [
          {
            "x": "2026-01",
            "y": 12
          },
          {
            "x": "2026-02",
            "y": 18
          }
        ]
      },
      "defaultProps": {
        "smooth": true,
        "area": true,
        "palette": "multi",
        "accent": "chart-1"
      },
      "maxRows": 5000,
      "version": "1.0.0"
    },
    {
      "type": "metric_glow",
      "kind": "chart",
      "name": "Métrica (glow)",
      "description": "Card de métrica única em destaque, com variação e efeito de brilho.",
      "source": "vitrine:metric-glow-card",
      "propsSchema": {
        "type": "object",
        "additionalProperties": false,
        "properties": {
          "label": {
            "type": "string",
            "description": "Rótulo da métrica (sobrescreve o `label` vindo dos dados). Se vazio, usa o label dos dados ou o nome do bloco."
          },
          "valueFormat": {
            "type": "string",
            "enum": [
              "BRL",
              "compactBRL",
              "number",
              "compactNumber",
              "percent"
            ],
            "default": "compactBRL",
            "description": "Formato PT-BR do valor em destaque. ENUM FECHADO (sem input livre). Substitui a formatação crua antiga.",
            "oneOf": [
              {
                "const": "BRL",
                "description": "formatBRL — moeda BRL completa (ex.: \"R$ 124.500,00\")."
              },
              {
                "const": "compactBRL",
                "description": "formatCompactBRL — moeda BRL compacta (ex.: \"R$ 124,5 mil\"). DEFAULT."
              },
              {
                "const": "number",
                "description": "formatNumberBR — número PT-BR com milhar (ex.: \"124.500\")."
              },
              {
                "const": "compactNumber",
                "description": "formatCompactNumberBR — número compacto (ex.: \"124,5 mil\")."
              },
              {
                "const": "percent",
                "description": "formatPercentBR — percentual a partir de FRAÇÃO (ex.: 0.125 → \"12,5%\")."
              }
            ]
          },
          "accent": {
            "type": "string",
            "enum": [
              "chart-1",
              "chart-2",
              "chart-3",
              "chart-4",
              "chart-5",
              "primary"
            ],
            "default": "chart-1",
            "description": "Cor do brilho/destaque do card. Aceita enum DS (chart-1..5, primary), classe Tailwind (bg-purple-500), ou cor CSS (#40E0D0, rgb(), linear-gradient(), var(--chart-1))."
          },
          "showDelta": {
            "type": "boolean",
            "default": true,
            "description": "Mostra a variação percentual (%) abaixo do valor. `false` esconde a variação mesmo quando há `delta` nos dados."
          },
          "deltaPolarity": {
            "type": "string",
            "enum": [
              "up-good",
              "up-bad"
            ],
            "default": "up-good",
            "description": "Semântica de cor da variação. ENUM FECHADO.",
            "oneOf": [
              {
                "const": "up-good",
                "description": "Subir é bom: variação positiva = verde, negativa = vermelho. DEFAULT (ex.: receita, vendas)."
              },
              {
                "const": "up-bad",
                "description": "Subir é ruim: variação positiva = vermelho, negativa = verde (ex.: inadimplência, custos, atrasos)."
              }
            ]
          }
        }
      },
      "dataContract": {
        "shape": "scalar",
        "spec": {
          "value": {
            "type": "number",
            "required": true
          },
          "label": {
            "type": "string",
            "required": false
          },
          "delta": {
            "type": "number",
            "required": false
          }
        },
        "example": {
          "value": 124500,
          "label": "Receita do mês",
          "unit": "BRL",
          "delta": 0.125
        }
      },
      "defaultProps": {
        "valueFormat": "compactBRL",
        "accent": "chart-1",
        "showDelta": true,
        "deltaPolarity": "up-good"
      },
      "version": "1.0.0"
    },
    {
      "type": "mobius_loop",
      "kind": "layout",
      "name": "Möbius Loop",
      "description": "Ícone animado (loop infinito) — ótimo como indicador de carregamento/processamento.",
      "source": "vitrine:mobius-loop-icon",
      "propsSchema": {
        "type": "object",
        "additionalProperties": false,
        "properties": {
          "size": {
            "type": "integer",
            "minimum": 16,
            "maximum": 240
          },
          "speed": {
            "type": "string",
            "enum": [
              "slow",
              "normal",
              "fast"
            ]
          }
        }
      },
      "defaultProps": {
        "size": 64,
        "speed": "normal"
      },
      "version": "1.0.0"
    },
    {
      "type": "pin_3d",
      "kind": "layout",
      "name": "3D Pin",
      "description": "Card com efeito de inclinação 3D e \"pin\" animado no hover.",
      "source": "vitrine:3d-pin",
      "propsSchema": {
        "type": "object",
        "additionalProperties": false,
        "properties": {
          "pinLabel": {
            "type": "string"
          },
          "href": {
            "type": "string"
          },
          "title": {
            "type": "string"
          },
          "description": {
            "type": "string"
          }
        }
      },
      "defaultProps": {
        "pinLabel": "relatorios.gov.br",
        "href": "#",
        "title": "Relatório de Arrecadação",
        "description": "Receita consolidada por tributo, com evolução mensal e metas."
      },
      "version": "1.0.0"
    },
    {
      "type": "progress_bar",
      "kind": "chart",
      "name": "Barra de Progresso",
      "description": "Progresso de um valor sobre uma escala (ex.: 68 de 100). Ótimo para metas.",
      "source": "vitrine:progress-bar-tremor",
      "propsSchema": {
        "type": "object",
        "additionalProperties": false,
        "properties": {
          "max": {
            "type": "number",
            "default": 100,
            "description": "Valor máximo da escala (denominador do %). Ex.: max=100 → value=68 vira 68%."
          },
          "variant": {
            "type": "string",
            "enum": [
              "default",
              "neutral",
              "warning",
              "error",
              "success"
            ],
            "default": "default",
            "description": "Cor SEMÂNTICA do preenchimento + trilho (default=azul, neutral=cinza, warning=amarelo, error=vermelho, success=verde). É SOBRESCRITO por `accent` quando este vier preenchido."
          },
          "accent": {
            "type": "string",
            "enum": [
              "chart-1",
              "chart-2",
              "chart-3",
              "chart-4",
              "chart-5",
              "primary"
            ],
            "description": "Cor CUSTOM do preenchimento. Quando preenchida, SOBRESCREVE o `variant`. Aceita enum DS (chart-1..5, primary), classe Tailwind (bg-purple-500) ou cor CSS crua (#40E0D0, rgb(), linear-gradient(), var(--chart-1))."
          },
          "showValue": {
            "type": "boolean",
            "default": true,
            "description": "Mostra (default) ou esconde o \"%\" exibido ao lado do rótulo do dado."
          }
        }
      },
      "dataContract": {
        "shape": "scalar",
        "spec": {
          "value": {
            "type": "number",
            "required": true
          },
          "label": {
            "type": "string",
            "required": false
          }
        },
        "example": {
          "value": 68,
          "label": "Uso da cota"
        }
      },
      "defaultProps": {
        "max": 100,
        "variant": "default",
        "showValue": true
      },
      "version": "1.0.0"
    },
    {
      "type": "progress_circle",
      "kind": "chart",
      "name": "Anel de Progresso",
      "description": "Progresso circular de um valor sobre uma escala (percentual no centro).",
      "source": "vitrine:progress-circle-tremor",
      "propsSchema": {
        "type": "object",
        "additionalProperties": false,
        "properties": {
          "max": {
            "type": "number",
            "default": 100,
            "description": "Valor máximo da escala (o 100% do anel). Default 100 — nesse caso o `value` já É um percentual. Com max ≠ 100, o anel mostra value/max e o tooltip explicita \"X de Y\"."
          },
          "variant": {
            "type": "string",
            "enum": [
              "default",
              "neutral",
              "warning",
              "error",
              "success"
            ],
            "default": "default",
            "description": "Tema de cor do anel (paleta semântica): default (azul), neutral (cinza), warning (amarelo), error (vermelho), success (verde). É IGNORADO quando `accent` está preenchido (accent sobrescreve o variant)."
          },
          "accent": {
            "type": "string",
            "enum": [
              "chart-1",
              "chart-2",
              "chart-3",
              "chart-4",
              "chart-5",
              "primary"
            ],
            "description": "Cor custom do arco. Quando preenchida, SOBRESCREVE o `variant`. Aceita enum DS (chart-1..5, primary), classe Tailwind de stroke (stroke-purple-500), ou cor CSS crua (#40E0D0, rgb(), linear-gradient(), var(--chart-1)). Vazio = usa o `variant`."
          }
        }
      },
      "dataContract": {
        "shape": "scalar",
        "spec": {
          "value": {
            "type": "number",
            "required": true
          },
          "label": {
            "type": "string",
            "required": false
          }
        },
        "example": {
          "value": 75,
          "label": "Conclusão"
        }
      },
      "defaultProps": {
        "max": 100,
        "variant": "default"
      },
      "version": "1.0.0"
    },
    {
      "type": "radial_gauge",
      "kind": "chart",
      "name": "Medidor Radial",
      "description": "Medidor (gauge) de um valor sobre uma escala — ótimo para metas e percentuais.",
      "source": "vitrine:radial-gauge",
      "propsSchema": {
        "type": "object",
        "additionalProperties": false,
        "properties": {
          "max": {
            "type": "number",
            "default": 100,
            "description": "Valor MÁXIMO da escala do medidor (fim do arco). Ex.: 100 para percentuais. O `value` dos dados é posicionado entre `min` e `max`."
          },
          "min": {
            "type": "number",
            "default": 0,
            "description": "Valor MÍNIMO da escala do medidor (início do arco). Default 0. Define o piso da escala junto com `max`."
          },
          "unit": {
            "type": "string",
            "description": "Unidade exibida ao lado do número no miolo (ex.: \"%\", \"km\", \"pts\"). Se ausente, usa a `unit` dos dados (data.unit)."
          },
          "accent": {
            "type": "string",
            "enum": [
              "chart-1",
              "chart-2",
              "chart-3",
              "chart-4",
              "chart-5",
              "primary"
            ],
            "default": "chart-1",
            "description": "Cor do ARCO do medidor (stroke + número central + brilho). Aceita enum DS (chart-1..5, primary), classe Tailwind (bg-purple-500), ou cor CSS (#40E0D0, rgb(), linear-gradient(), var(--chart-1))."
          }
        }
      },
      "dataContract": {
        "shape": "scalar",
        "spec": {
          "value": {
            "type": "number",
            "required": true
          },
          "label": {
            "type": "string",
            "required": false
          },
          "unit": {
            "type": "string",
            "required": false
          }
        },
        "example": {
          "value": 72,
          "label": "Cobertura",
          "unit": "%"
        }
      },
      "defaultProps": {
        "max": 100,
        "min": 0,
        "accent": "chart-1"
      },
      "version": "1.0.0"
    },
    {
      "type": "resizable_panels",
      "kind": "layout",
      "name": "Painéis Redimensionáveis",
      "description": "Dois painéis lado a lado com divisória arrastável.",
      "source": "vitrine:resizable",
      "propsSchema": {
        "type": "object",
        "additionalProperties": false,
        "properties": {
          "direction": {
            "type": "string",
            "enum": [
              "horizontal",
              "vertical"
            ]
          },
          "leftLabel": {
            "type": "string"
          },
          "rightLabel": {
            "type": "string"
          }
        }
      },
      "defaultProps": {
        "direction": "horizontal",
        "leftLabel": "Filtros",
        "rightLabel": "Resultado"
      },
      "version": "1.0.0"
    },
    {
      "type": "rich_text",
      "kind": "text",
      "name": "Texto rico",
      "description": "Bloco narrativo em markdown (análise do relatório). Sem dados.",
      "source": "custom",
      "propsSchema": {
        "type": "object",
        "additionalProperties": false,
        "required": [
          "markdown"
        ],
        "properties": {
          "markdown": {
            "type": "string"
          }
        }
      },
      "defaultProps": {
        "markdown": ""
      },
      "version": "1.0.0"
    },
    {
      "type": "scatter_chart",
      "kind": "chart",
      "name": "Dispersão (scatter)",
      "description": "Correlação entre duas variáveis numéricas (x × y); `series` colore por categoria.",
      "source": "vitrine:scatter-chart-tremor",
      "propsSchema": {
        "type": "object",
        "additionalProperties": false,
        "properties": {
          "showLegend": {
            "type": "boolean",
            "default": true,
            "description": "Exibe legenda clicável acima do chart (uma bolinha por categoria, com clique para dim das outras)."
          },
          "showGridLines": {
            "type": "boolean",
            "default": true,
            "description": "Exibe linhas de grade horizontais e verticais tracejadas."
          },
          "palette": {
            "type": "string",
            "enum": [
              "single",
              "multi",
              "none"
            ],
            "default": "multi",
            "description": "Modo de paleta: \"multi\" (default) = cicla chart-1..5 por categoria; \"single\" = força accent em todas (1 cor); \"none\" = sem distinção (usa a palette cíclica padrão)."
          },
          "accent": {
            "type": "string",
            "enum": [
              "chart-1",
              "chart-2",
              "chart-3",
              "chart-4",
              "chart-5",
              "primary"
            ],
            "default": "chart-1",
            "description": "Cor ÚNICA aplicada a TODAS as categorias (vence palette cíclica). Aceita enum DS (chart-1..5, primary), classe Tailwind (bg-purple-500), ou cor CSS (#40E0D0, rgb(), linear-gradient(), var(--chart-1))."
          }
        }
      },
      "dataContract": {
        "shape": "series",
        "spec": {
          "x": {
            "type": "number",
            "required": true
          },
          "y": {
            "type": "number",
            "required": true
          },
          "series": {
            "type": "category",
            "required": false
          }
        },
        "example": [
          {
            "x": 12,
            "y": 40,
            "series": "Zona A"
          },
          {
            "x": 28,
            "y": 55,
            "series": "Zona B"
          }
        ]
      },
      "defaultProps": {
        "showLegend": true,
        "showGridLines": true,
        "palette": "multi",
        "accent": "chart-1"
      },
      "maxRows": 5000,
      "version": "1.0.0"
    },
    {
      "type": "section",
      "kind": "layout",
      "name": "Seção (Container)",
      "description": "Container hierárquico: agrupa sub-blocos num card com header (título + subtítulo) e corpo em grid de 12 colunas. Permite composição: seção dentro de seção, sumário executivo, etc.",
      "source": "custom",
      "propsSchema": {
        "type": "object",
        "additionalProperties": false,
        "required": [
          "title"
        ],
        "properties": {
          "title": {
            "type": "string",
            "description": "Título da seção (header)."
          },
          "subtitle": {
            "type": "string",
            "description": "Subtítulo / descrição curta."
          },
          "variant": {
            "type": "string",
            "enum": [
              "card",
              "framed"
            ],
            "description": "Estilo visual do container. Default: 'card'."
          }
        }
      },
      "defaultProps": {
        "title": "Seção",
        "variant": "card"
      },
      "version": "1.0.0"
    },
    {
      "type": "sheet",
      "kind": "layout",
      "name": "Sheet (painel lateral)",
      "description": "Botão que abre um painel deslizante lateral com título e descrição.",
      "source": "vitrine:sheet",
      "propsSchema": {
        "type": "object",
        "additionalProperties": false,
        "properties": {
          "triggerLabel": {
            "type": "string"
          },
          "title": {
            "type": "string"
          },
          "description": {
            "type": "string"
          },
          "side": {
            "type": "string",
            "enum": [
              "top",
              "right",
              "bottom",
              "left"
            ]
          }
        }
      },
      "defaultProps": {
        "triggerLabel": "Abrir painel",
        "title": "Detalhes do indicador",
        "description": "Informações complementares sobre a métrica selecionada.",
        "side": "right"
      },
      "version": "1.0.0"
    },
    {
      "type": "signal_card",
      "kind": "chart",
      "name": "Signal Card",
      "description": "KPI com mini-sparkline e tendência. Recebe uma série; destaca o último valor.",
      "source": "vitrine:signal-card",
      "propsSchema": {
        "type": "object",
        "additionalProperties": false,
        "properties": {
          "label": {
            "type": "string",
            "default": "Sinal",
            "description": "Rótulo curto do sinal exibido acima do valor (ex.: \"Latência p95\", \"Arrecadação\")."
          },
          "valueFormat": {
            "type": "string",
            "enum": [
              "BRL",
              "compactBRL",
              "number",
              "compactNumber",
              "percent"
            ],
            "default": "compactNumber",
            "description": "Formato PT-BR do valor em destaque (último ponto da série). ENUM FECHADO (sem input livre). Default \"compactNumber\".",
            "oneOf": [
              {
                "const": "BRL",
                "description": "formatBRL — moeda BRL completa (ex.: \"R$ 2.609.946.157,73\")."
              },
              {
                "const": "compactBRL",
                "description": "formatCompactBRL — moeda BRL compacta (ex.: \"R$ 2,61 bi\")."
              },
              {
                "const": "number",
                "description": "formatNumberBR — número PT-BR com milhar (ex.: \"1.234.567,8\")."
              },
              {
                "const": "compactNumber",
                "description": "formatCompactNumberBR — número compacto (ex.: \"2,61 bi\"). DEFAULT."
              },
              {
                "const": "percent",
                "description": "formatPercentBR — percentual a partir de FRAÇÃO (ex.: 0.125 → \"12,5%\")."
              }
            ]
          },
          "accent": {
            "type": "string",
            "enum": [
              "chart-1",
              "chart-2",
              "chart-3",
              "chart-4",
              "chart-5",
              "primary"
            ],
            "default": "chart-1",
            "description": "Cor da sparkline (pinta o traço/preenchimento, NÃO o fundo). Aceita enum DS (chart-1..5, primary), classe Tailwind (stroke-purple-500), ou cor CSS (#40E0D0, rgb(), var(--chart-1))."
          },
          "trendPolarity": {
            "type": "string",
            "enum": [
              "up-good",
              "up-bad"
            ],
            "default": "up-good",
            "description": "Direção considerada \"boa\": \"up-good\" (subir = verde, padrão) ou \"up-bad\" (subir = vermelho, ex.: latência/erro)."
          },
          "trendBasis": {
            "type": "string",
            "enum": [
              "first-vs-last",
              "prev-vs-last"
            ],
            "default": "prev-vs-last",
            "description": "Base do cálculo da tendência: \"prev-vs-last\" (default) = último vs penúltimo (variação mais recente); \"first-vs-last\" = último vs primeiro (variação no período inteiro)."
          },
          "showSparkline": {
            "type": "boolean",
            "default": true,
            "description": "Mostra (true, default) ou esconde (false) a mini-sparkline abaixo do valor."
          }
        }
      },
      "dataContract": {
        "shape": "series",
        "spec": {
          "x": {
            "type": "category",
            "required": false
          },
          "y": {
            "type": "number",
            "required": true
          }
        },
        "example": [
          {
            "x": "1",
            "y": 48
          },
          {
            "x": "2",
            "y": 62
          }
        ]
      },
      "defaultProps": {
        "label": "Sinal",
        "valueFormat": "compactNumber",
        "accent": "chart-1",
        "trendPolarity": "up-good",
        "trendBasis": "prev-vs-last",
        "showSparkline": true
      },
      "maxRows": 1000,
      "version": "1.0.0"
    },
    {
      "type": "spark_chart",
      "kind": "chart",
      "name": "Sparkline",
      "description": "Minigráfico de tendência (sem eixos) — ótimo ao lado de um KPI.",
      "source": "vitrine:spark-chart-tremor",
      "propsSchema": {
        "type": "object",
        "additionalProperties": false,
        "properties": {
          "type": {
            "type": "string",
            "enum": [
              "area",
              "bar",
              "line"
            ],
            "default": "area",
            "description": "Variante do spark chart: \"area\" (default, com gradiente), \"bar\" (colunas) ou \"line\" (linha sem preenchimento)."
          },
          "curveType": {
            "type": "string",
            "enum": [
              "linear",
              "monotone",
              "step"
            ],
            "default": "monotone",
            "description": "Curva usada em type=\"area\" e type=\"line\": \"linear\" (reta entre pontos), \"monotone\" (suavizada sem overshoot) ou \"step\" (degraus)."
          },
          "palette": {
            "type": "string",
            "enum": [
              "single",
              "multi",
              "none"
            ],
            "default": "single",
            "description": "Modo de paleta: \"single\" (default) = 1 cor (accent) na série; \"multi\" = GRADIENTE multicolor (chart-1..5) ao longo da série (spark é single-série, então multi vira um arco-íris contínuo, não fatias); \"none\" = comportamento single."
          },
          "accent": {
            "type": "string",
            "enum": [
              "chart-1",
              "chart-2",
              "chart-3",
              "chart-4",
              "chart-5",
              "primary"
            ],
            "default": "chart-1",
            "description": "Cor da SÉRIE (pinta o traço/preenchimento do gráfico, NÃO o fundo). Aceita enum DS (chart-1..5, primary), classe Tailwind (stroke-purple-500), ou cor CSS (#40E0D0, rgb(), var(--chart-1)). Usada em palette \"single\"/\"none\"; em \"multi\" a paleta multicolor vence."
          }
        }
      },
      "dataContract": {
        "shape": "series",
        "spec": {
          "x": {
            "type": "category",
            "required": false
          },
          "y": {
            "type": "number",
            "required": true
          }
        },
        "example": [
          {
            "x": "1",
            "y": 5
          },
          {
            "x": "2",
            "y": 8
          }
        ]
      },
      "defaultProps": {
        "type": "area",
        "curveType": "monotone",
        "palette": "single",
        "accent": "chart-1"
      },
      "maxRows": 5000,
      "version": "1.0.0"
    },
    {
      "type": "stat_tile",
      "kind": "chart",
      "name": "Stat Tile",
      "description": "Ladrilho compacto de estatística (valor + variação) para grades de KPIs.",
      "source": "vitrine:stat-tile",
      "propsSchema": {
        "type": "object",
        "additionalProperties": false,
        "properties": {
          "label": {
            "type": "string",
            "description": "Rótulo do ladrilho. Sobrescreve o `label` derivado dos dados (data.label). Se ausente, usa data.label e, por fim, o nome do bloco."
          },
          "valueFormat": {
            "type": "string",
            "enum": [
              "BRL",
              "compactBRL",
              "number",
              "compactNumber",
              "percent"
            ],
            "default": "compactNumber",
            "description": "Formato PT-BR do valor exibido. ENUM FECHADO (sem input livre). Substitui o prefixo de moeda hardcoded.",
            "oneOf": [
              {
                "const": "BRL",
                "description": "formatBRL — moeda BRL completa (ex.: \"R$ 2.609.946.157,73\")."
              },
              {
                "const": "compactBRL",
                "description": "formatCompactBRL — moeda BRL compacta (ex.: \"R$ 2,61 bi\")."
              },
              {
                "const": "number",
                "description": "formatNumberBR — número PT-BR com milhar (ex.: \"1.234.567,8\")."
              },
              {
                "const": "compactNumber",
                "description": "formatCompactNumberBR — número compacto (ex.: \"2,61 bi\"). DEFAULT."
              },
              {
                "const": "percent",
                "description": "formatPercentBR — percentual a partir de FRAÇÃO (ex.: 0.125 → \"12,5%\")."
              }
            ]
          },
          "accent": {
            "type": "string",
            "enum": [
              "chart-1",
              "chart-2",
              "chart-3",
              "chart-4",
              "chart-5",
              "primary"
            ],
            "default": "chart-1",
            "description": "Cor de destaque (barra lateral). Aceita enum DS (chart-1..5, primary), classe Tailwind (bg-purple-500), ou cor CSS (#40E0D0, rgb(), linear-gradient(), var(--chart-1))."
          },
          "showDelta": {
            "type": "boolean",
            "default": true,
            "description": "Mostra a variação (delta) quando os dados trazem `delta`. `false` esconde a variação."
          },
          "deltaPolarity": {
            "type": "string",
            "enum": [
              "up-good",
              "up-bad"
            ],
            "default": "up-good",
            "description": "Polaridade da variação: \"up-good\" (subir é bom → positivo verde) | \"up-bad\" (subir é ruim → positivo vermelho).",
            "oneOf": [
              {
                "const": "up-good",
                "description": "Subir é bom: delta positivo = verde, negativo = vermelho. DEFAULT."
              },
              {
                "const": "up-bad",
                "description": "Subir é ruim: delta positivo = vermelho, negativo = verde."
              }
            ]
          },
          "hint": {
            "type": "string",
            "description": "Texto auxiliar exibido ao lado do delta (ex.: \"vs. ontem\")."
          }
        }
      },
      "dataContract": {
        "shape": "scalar",
        "spec": {
          "value": {
            "type": "number",
            "required": true
          },
          "label": {
            "type": "string",
            "required": false
          },
          "delta": {
            "type": "number",
            "required": false
          }
        },
        "example": {
          "value": 8420,
          "label": "Eventos hoje",
          "delta": 0.06
        }
      },
      "defaultProps": {
        "valueFormat": "compactNumber",
        "accent": "chart-1",
        "showDelta": true,
        "deltaPolarity": "up-good"
      },
      "version": "1.0.0"
    },
    {
      "type": "table",
      "kind": "chart",
      "name": "Tabela",
      "description": "Dados tabulares crus com colunas tipadas.",
      "source": "vitrine:data-table",
      "propsSchema": {
        "type": "object",
        "additionalProperties": false,
        "properties": {
          "pageSize": {
            "type": "integer",
            "minimum": 1
          },
          "dense": {
            "type": "boolean"
          }
        }
      },
      "dataContract": {
        "shape": "table",
        "spec": {
          "columns": {
            "type": "array",
            "required": true
          },
          "rows": {
            "type": "array",
            "required": true
          }
        },
        "example": {
          "columns": [
            {
              "key": "municipio",
              "label": "Município",
              "type": "string"
            },
            {
              "key": "valor",
              "label": "Valor",
              "type": "number"
            }
          ],
          "rows": [
            {
              "municipio": "Centro",
              "valor": 1000
            }
          ]
        }
      },
      "defaultProps": {
        "pageSize": 10
      },
      "maxRows": 5000,
      "version": "1.0.0"
    },
    {
      "type": "title",
      "kind": "title",
      "name": "Título",
      "description": "Bloco narrativo de título/seção. Sem dados.",
      "source": "custom",
      "propsSchema": {
        "type": "object",
        "additionalProperties": false,
        "required": [
          "text"
        ],
        "properties": {
          "text": {
            "type": "string"
          },
          "level": {
            "type": "integer",
            "minimum": 1,
            "maximum": 6
          },
          "align": {
            "type": "string",
            "enum": [
              "left",
              "center",
              "right"
            ]
          }
        }
      },
      "defaultProps": {
        "level": 2,
        "align": "left"
      },
      "version": "1.0.0"
    },
    {
      "type": "tooltip_card",
      "kind": "layout",
      "name": "Tooltip Card",
      "description": "Tooltip rico que segue o cursor e exibe um card de conteúdo.",
      "source": "vitrine:tooltip-card",
      "propsSchema": {
        "type": "object",
        "additionalProperties": false,
        "properties": {
          "triggerLabel": {
            "type": "string"
          },
          "content": {
            "type": "string"
          }
        }
      },
      "defaultProps": {
        "triggerLabel": "Detalhes do contribuinte",
        "content": "CPF/CNPJ, situação cadastral e débitos em aberto do contribuinte selecionado."
      },
      "version": "1.0.0"
    },
    {
      "type": "tooltip_fluid",
      "kind": "layout",
      "name": "Tooltip Fluido",
      "description": "Tooltip com animação suave exibido ao focar/passar o mouse no gatilho.",
      "source": "vitrine:tooltip-fluid",
      "propsSchema": {
        "type": "object",
        "additionalProperties": false,
        "properties": {
          "triggerLabel": {
            "type": "string"
          },
          "content": {
            "type": "string"
          },
          "side": {
            "type": "string",
            "enum": [
              "top",
              "right",
              "bottom",
              "left"
            ]
          }
        }
      },
      "defaultProps": {
        "triggerLabel": "Passe o mouse",
        "content": "Receita acumulada no exercício",
        "side": "top"
      },
      "version": "1.0.0"
    }
  ]
}
